FONT-LICENSE
LICENSE
MANIFEST.in
setup.py
TermRecord.egg-info/PKG-INFO
TermRecord.egg-info/SOURCES.txt
TermRecord.egg-info/dependency_links.txt
TermRecord.egg-info/requires.txt
TermRecord.egg-info/top_level.txt
bin/TermRecord
termrecord/__init__.py
termrecord/templates/base.jinja2
termrecord/templates/dynamic.jinja2
termrecord/templates/static.jinja2