Metadata-Version: 1.1
Name: TermRecord
Version: 1.2.5
Summary: A simple terminal session recorder with easy-to-share HTML output!
Home-page: http://github.com/theonewolf/TermRecord
Author: Wolfgang Richter
Author-email: wolfgang.richter@gmail.com
License: MIT
Platform: UNKNOWN
Classifier: Development Status :: 5 - Production/Stable
Classifier: Environment :: Console
Classifier: Intended Audience :: Developers
Classifier: Intended Audience :: Science/Research
Classifier: Intended Audience :: System Administrators
Classifier: Intended Audience :: Education
Classifier: License :: OSI Approved :: MIT License
Classifier: Operating System :: MacOS :: MacOS X
Classifier: Operating System :: POSIX :: Linux
Classifier: Programming Language :: Python :: 2
Classifier: Programming Language :: Python :: 3
Classifier: Topic :: System :: Logging
Classifier: Topic :: Terminals
